Placer_package/__init__.py
Placer_package/destroyer.py
Placer_package/ether.py
Placer_package/shortr.py
Placer_package-0.1.2.dist-info/LICENSE
Placer_package-0.1.2.dist-info/METADATA
Placer_package-0.1.2.dist-info/WHEEL
Placer_package-0.1.2.dist-info/top_level.txt
Placer_package-0.1.2.dist-info/RECORD
