Metadata-Version: 2.1
Name: Placer-package
Version: 0.1.2
Summary: A collection of modules created by Placer_0884
Home-page: https://github.com/placer0884/Placer_package
Author: Placer_0884
Author-email: placer0884@gmail.com
Project-URL: Bug Tracker, https://github.com/pypa/Placer_package/issues
Classifier: Programming Language :: Python :: 3
Classifier: License :: Other/Proprietary License
Classifier: Operating System :: OS Independent
Requires-Python: >=3.8
License-File: LICENSE
